vizcovidfr/__init__.py
vizcovidfr/barplots/__init__.py
vizcovidfr/barplots/barplots.py
vizcovidfr/heatmaps/__init__.py
vizcovidfr/heatmaps/heatmap.py
vizcovidfr/line_charts/__init__.py
vizcovidfr/line_charts/line_charts.py
vizcovidfr/loads/__init__.py
vizcovidfr/loads/load_datasets.py
vizcovidfr/maps/__init__.py
vizcovidfr/maps/maps.py
vizcovidfr/pie_charts/__init__.py
vizcovidfr/pie_charts/pie_chart.py
vizcovidfr/prediction/__init__.py
vizcovidfr/prediction/prediction.py
vizcovidfr/preprocesses/__init__.py
vizcovidfr/preprocesses/preprocess_chiffres_cles.py
vizcovidfr/preprocesses/preprocess_classe_age.py
vizcovidfr/preprocesses/preprocess_heatmaps.py
vizcovidfr/preprocesses/preprocess_maps.py
vizcovidfr/preprocesses/preprocess_positivity.py
vizcovidfr/regression/__init__.py
vizcovidfr/regression/regression.py
vizcovidfr/sparse/__init__.py
vizcovidfr/sparse/sparse.py
vizcovidfr/tests/__init__.py
vizcovidfr/tests/test_vizcovidfr.py
vizcovidfr-0.0.3.dist-info/METADATA
vizcovidfr-0.0.3.dist-info/WHEEL
vizcovidfr-0.0.3.dist-info/top_level.txt
vizcovidfr-0.0.3.dist-info/RECORD
