Metadata-Version: 2.1
Name: vizcovidfr
Version: 0.0.3
Summary: A python package to visualize spatial evolution of Covid19 cases in France
Home-page: https://github.com/AmelieVernay/vizcovidfr
Author: Foux Quentin ; Llinares Laurent ; Nicolas Alexandre ; Vernay Amelie
Author-email: quentin.foux@etu.umontpellier.fr, laurent.llinares@etu.umontpellier.fr, alexandre.nicolas@etu.umontpellier.fr, amelie.vernay@etu.umontpellier.fr
License: MIT
Platform: UNKNOWN
